automatagen/__init__.py
automatagen/automatagen.py
automatagen-0.2.post4.dist-info/LICENSE
automatagen-0.2.post4.dist-info/METADATA
automatagen-0.2.post4.dist-info/WHEEL
automatagen-0.2.post4.dist-info/top_level.txt
automatagen-0.2.post4.dist-info/RECORD
