Metadata-Version: 2.1
Name: automatagen
Version: 0.2.post4
Summary: Generate random terrain using cellular automata.
Home-page: https://github.com/PetarPeychev/automatagen
Author: PetarPeychev
Author-email: petarpeychev98@gmail.com
License: UNKNOWN
Platform: UNKNOWN
Classifier: Programming Language :: Python :: 3
Classifier: License :: Public Domain
Classifier: Operating System :: OS Independent
